LICENSE
README.md
pyproject.toml
setup.cfg
setup.py
src/byond/__init__.py
src/byond/topic.py
src/byond_topic.egg-info/PKG-INFO
src/byond_topic.egg-info/SOURCES.txt
src/byond_topic.egg-info/dependency_links.txt
src/byond_topic.egg-info/top_level.txt