Metadata-Version: 2.4
Name: byond-topic
Version: 0.1.2
Summary: Sending Topic packets to BYOND servers, and receive responses
Home-page: https://github.com/TamberP/byond.topic
Author: Tamber
Author-email: tamber@furryhelix.co.uk
Classifier: Programming Language :: Python :: 3.9
Classifier: License :: OSI Approved :: BSD License
Requires-Python: >=3.8
License-File: LICENSE
Dynamic: license-file
